globygon/__init__.py
globygon/catalog.py
globygon/globygon.py
globygon-1.0.dist-info/LICENSE.txt
globygon-1.0.dist-info/METADATA
globygon-1.0.dist-info/WHEEL
globygon-1.0.dist-info/top_level.txt
globygon-1.0.dist-info/RECORD
